streamAPI/__init__.py
streamAPI/testHelper.py
streamAPI/stream/__init__.py
streamAPI/stream/decos.py
streamAPI/stream/exception.py
streamAPI/stream/optional.py
streamAPI/stream/parallelStream.py
streamAPI/stream/stream.py
streamAPI/stream/streamHelper.py
streamAPI/stream/TO/TerminalOperations.py
streamAPI/stream/TO/__init__.py
streamAPI/utility/Types.py
streamAPI/utility/__init__.py
streamAPI/utility/utils.py
streamapi-2.7.2.dist-info/licenses/LICENSE
streamapi-2.7.2.dist-info/METADATA
streamapi-2.7.2.dist-info/WHEEL
streamapi-2.7.2.dist-info/top_level.txt
streamapi-2.7.2.dist-info/RECORD
