Metadata-Version: 2.4
Name: streamAPI
Version: 2.7.2
Summary: basics utility and stream processing functionality
Author-email: Shiv Krishna Jaiswal <shivkj001@gmail.com>
Maintainer-email: Shiv Krishna Jaiswal <shivkj001@gmail.com>
License: MIT License
Project-URL: Homepage, https://github.com/ShivKJ/Stream
Project-URL: Documentation, https://github.com/ShivKJ/Stream
Project-URL: Repository, https://github.com/ShivKJ/Stream
Project-URL: Issues, https://github.com/ShivKJ/Stream/issues
Keywords: stream,streamAPI,fluent
Classifier: Development Status :: 4 - Beta
Classifier: Intended Audience :: Developers
Classifier: Topic :: Software Development :: Build Tools
Classifier: License :: OSI Approved :: MIT License
Classifier: Programming Language :: Python :: 3.8
Classifier: Programming Language :: Python :: 3.9
Classifier: Programming Language :: Python :: 3.10
Classifier: Programming Language :: Python :: 3.12
Requires-Python: >=3.8
License-File: LICENSE
Requires-Dist: decorator>=5.2.1
Requires-Dist: psutil>=7.0.0
Requires-Dist: python-dateutil>=2.9.0.post0
Provides-Extra: test
Requires-Dist: pytest>=8.2.2; extra == "test"
Requires-Dist: pytest-sugar>=1.0.0; extra == "test"
Dynamic: license-file
